shiftai/__init__.py
shiftai/client.py
shiftai/api/__init__.py
shiftai/api/agents_api.py
shiftai/api/analytics_api.py
shiftai/api/conversations_api.py
shiftai/api/messages_api.py
shiftai/api/platform_api.py
shiftai/api/platform_session_api.py
shiftai/api/users_api.py
shiftai/api/internal/__init__.py
shiftai/api/internal/trulens_api.py
shiftai/http/__init__.py
shiftai/http/exceptions.py
shiftai/http/http_client.py
shiftai/models/__init__.py
shiftaiagenticinfra_sdk_python-0.0.7.dist-info/METADATA
shiftaiagenticinfra_sdk_python-0.0.7.dist-info/WHEEL
shiftaiagenticinfra_sdk_python-0.0.7.dist-info/top_level.txt
shiftaiagenticinfra_sdk_python-0.0.7.dist-info/RECORD
