Metadata-Version: 2.4
Name: shiftaiagenticinfra-sdk-python
Version: 0.0.7
Summary: Shiftai Agentic Infra Python SDK
Author: ShiftAI
Author-email: ShiftAI <s.tadakamalla@theshiftai.in>
License: MIT
Project-URL: Website, https://theshiftai.in
Project-URL: LinkedIn, https://www.linkedin.com/company/theshiftai-in
Keywords: shiftAI,agentic_infra,shiftaiagenticinfra,shiftaiagenticinfra_sdk,agenticinfra_sdk,infrastructure,sdk,api,client
Classifier: Development Status :: 4 - Beta
Classifier: Intended Audience :: Developers
Classifier: License :: OSI Approved :: MIT License
Classifier: Programming Language :: Python :: 3
Classifier: Programming Language :: Python :: 3.8
Classifier: Programming Language :: Python :: 3.9
Classifier: Programming Language :: Python :: 3.10
Classifier: Programming Language :: Python :: 3.11
Classifier: Programming Language :: Python :: 3.12
Requires-Python: >=3.8
Requires-Dist: httpx>=0.24.0
Provides-Extra: dev
Requires-Dist: pytest>=7.0.0; extra == "dev"
Requires-Dist: pytest-asyncio>=0.21.0; extra == "dev"
Requires-Dist: pytest-cov>=4.0.0; extra == "dev"
Dynamic: author
Dynamic: requires-python
